sluth/__init__.py
sluth/_version.py
sluth/py.typed
sluth/walker.py
sluth-0.2.0.dist-info/LICENSE
sluth-0.2.0.dist-info/METADATA
sluth-0.2.0.dist-info/WHEEL
sluth-0.2.0.dist-info/RECORD
