Metadata-Version: 2.1
Name: sluth
Version: 0.2.0
Summary: 
Home-page: https://github.com/bentheiii/sluth
License: MIT
Author: ben avrahami
Author-email: avrahami.ben@gmail.com
Requires-Python: >=3.10,<4.0
Classifier: License :: OSI Approved :: MIT License
Classifier: Programming Language :: Python :: 3
Classifier: Programming Language :: Python :: 3.10
Classifier: Programming Language :: Python :: 3.11
Classifier: Programming Language :: Python :: 3.12
Project-URL: Repository, https://github.com/bentheiii/sluth
